github_actions_test_k1shk1n/__init__.py
github_actions_test_k1shk1n/main.py
github_actions_test_k1shk1n-0.0.4.dist-info/METADATA
github_actions_test_k1shk1n-0.0.4.dist-info/WHEEL
github_actions_test_k1shk1n-0.0.4.dist-info/entry_points.txt
github_actions_test_k1shk1n-0.0.4.dist-info/RECORD
