Metadata-Version: 2.3
Name: github-actions-test-k1shk1n
Version: 0.0.4
Summary: 
Requires-Python: >=3.10,<4.0
Classifier: Programming Language :: Python :: 3
Classifier: Programming Language :: Python :: 3.10
Classifier: Programming Language :: Python :: 3.11
Classifier: Programming Language :: Python :: 3.12
Classifier: Programming Language :: Python :: 3.13
Requires-Dist: twine (>=6.0.1,<7.0.0)
